<soap:Envelope xmlns:soap="http://schemas.xmlsoap.org/soap/envelope/">
   <soap:Body>
      <ns2:getDataResponse xmlns:ns2="http://service.via.med.va.gov/">
         <ns2:PatientMedicalRecordTO>
            <immunizations>
               <count>1</count>
               <arrays>
                  <taggedImmunizationArray>
                     <count>8</count>
                     <tag>984</tag>
                     <immunizations>
                        <immunizationTO>
                           <administeredDate>3231031.1316</administeredDate>
                           <comments>Entered Booster as series</comments>
                           <contraindicated>0</contraindicated>
                           <cptCode>
                              <id>90651</id>
                              <name>9VHPV VACCINE 2/3 DOSE IM</name>
                           </cptCode>
                           <encounter>
                              <provider>
                                 <name>TESTdavis,William</name>
                              </provider>
                              <location>
                                 <name>23 HOUR OBSERVATION</name>
                              </location>
                              <visitId>6449872</visitId>
                              <facility>
                                 <sitecode>984</sitecode>
                                 <name>DAYTSHR TEST LAB</name>
                              </facility>
                           </encounter>
                           <id>125308</id>
                           <name>HPV9</name>
                           <series>BOOSTER</series>
                        </immunizationTO>
                        <immunizationTO>
                           <administeredDate>3231027.1</administeredDate>
                           <comments>Immunization test with Williams TESTdavis</comments>
                           <contraindicated>0</contraindicated>
                           <cptCode>
                              <id>90732</id>
                              <name>PPSV23 VACC 2 YRS+ SUBQ/IM</name>
                           </cptCode>
                           <encounter>
                              <provider>
                                 <name>TESTmiller,David</name>
                              </provider>
                              <location>
                                 <name>ADTP BURNETT</name>
                              </location>
                              <visitId>6449727</visitId>
                              <facility>
                                 <sitecode>984</sitecode>
                                 <name>DAYTSHR TEST LAB</name>
                              </facility>
                           </encounter>
                           <id>125307</id>
                           <name>PNEUMOCOCCAL POLYSACCHARIDE PPV23</name>
                           <series>SERIES 4</series>
                        </immunizationTO>
                        <immunizationTO>
                           <administeredDate>3231013.1115</administeredDate>
                           <comments>test series 1</comments>
                           <contraindicated>0</contraindicated>
                           <cptCode>
                              <id>90750</id>
                              <name>HZV VACC RECOMBINANT IM</name>
                           </cptCode>
                           <encounter>
                              <provider>
                                 <name>TESTdavis,William</name>
                              </provider>
                              <location>
                                 <name>AUDIOLOGY FELLOW (PM)</name>
                              </location>
                              <visitId>6449195</visitId>
                              <facility>
                                 <sitecode>984</sitecode>
                                 <name>DAYTSHR TEST LAB</name>
                              </facility>
                           </encounter>
                           <id>125286</id>
                           <name>ZOSTER RECOMBINANT</name>
                           <series>SERIES 1</series>
                        </immunizationTO>
                        <immunizationTO>
                           <administeredDate>3231013.1049</administeredDate>
                           <comments>Yellow</comments>
                           <contraindicated>0</contraindicated>
                           <cptCode>
                              <id>90717</id>
                              <name>YELLOW FEVER VACCINE SUBQ</name>
                           </cptCode>
                           <encounter>
                              <provider>
                                 <name>TESTdavis,William</name>
                              </provider>
                              <location>
                                 <name>ADULT DAY HEALTH CARE</name>
                              </location>
                              <visitId>6449192</visitId>
                              <facility>
                                 <sitecode>984</sitecode>
                                 <name>DAYTSHR TEST LAB</name>
                              </facility>
                           </encounter>
                           <id>125285</id>
                           <name>YELLOW FEVER</name>
                           <series>COMPLETE</series>
                        </immunizationTO>
                        <immunizationTO>
                           <administeredDate>3220818.162923</administeredDate>
                           <contraindicated>0</contraindicated>
                           <encounter>
                              <location>
                                 <name>ADMISSIONS (LOC)</name>
                              </location>
                              <visitId>6433382</visitId>
                              <facility>
                                 <sitecode>552</sitecode>
                                 <name>DAYTON</name>
                              </facility>
                           </encounter>
                           <id>124694</id>
                           <name>COVID-19 (MODERNA), MRNA, LNP-S, PF, 100 MCG/0.5ML DOSE OR 50 MCG/0.25ML DOSE</name>
                        </immunizationTO>
                        <immunizationTO>
                           <administeredDate>3220818.162923</administeredDate>
                           <contraindicated>0</contraindicated>
                           <encounter>
                              <location>
                                 <name>ADMISSIONS (LOC)</name>
                              </location>
                              <visitId>6433382</visitId>
                              <facility>
                                 <sitecode>552</sitecode>
                                 <name>DAYTON</name>
                              </facility>
                           </encounter>
                           <id>124695</id>
                           <name>DENGUE FEVER TETRAVALENT</name>
                        </immunizationTO>
                        <immunizationTO>
                           <administeredDate>3220818.162923</administeredDate>
                           <contraindicated>0</contraindicated>
                           <cptCode>
                              <id>90707</id>
                              <name>MMR VACCINE SC</name>
                           </cptCode>
                           <encounter>
                              <location>
                                 <name>ADMISSIONS (LOC)</name>
                              </location>
                              <visitId>6433382</visitId>
                              <facility>
                                 <sitecode>552</sitecode>
                                 <name>DAYTON</name>
                              </facility>
                           </encounter>
                           <id>124696</id>
                           <name>MMR</name>
                        </immunizationTO>
                        <immunizationTO>
                           <administeredDate>3220818.162923</administeredDate>
                           <contraindicated>0</contraindicated>
                           <encounter>
                              <location>
                                 <name>ADMISSIONS (LOC)</name>
                              </location>
                              <visitId>6433382</visitId>
                              <facility>
                                 <sitecode>552</sitecode>
                                 <name>DAYTON</name>
                              </facility>
                           </encounter>
                           <id>124697</id>
                           <name>HEP B, ADULT</name>
                        </immunizationTO>
                     </immunizations>
                  </taggedImmunizationArray>
               </arrays>
            </immunizations>
            <patient>
               <count>1</count>
               <arrays>
                  <taggedPatientArray>
                     <count>1</count>
                     <tag>984</tag>
                     <patients>
                        <patientTO>
                           <name>CASEY,VETERAN</name>
                           <patientName>CASEY,VETERAN</patientName>
                           <mpiPid>1013704789</mpiPid>
                           <mpiChecksum>992505</mpiChecksum>
                           <localPid>552164830</localPid>
                           <confidentiality>
                              <tag>0</tag>
                           </confidentiality>
                           <patientFlags>
                              <count>0</count>
                           </patientFlags>
                        </patientTO>
                     </patients>
                  </taggedPatientArray>
               </arrays>
            </patient>
         </ns2:PatientMedicalRecordTO>
      </ns2:getDataResponse>
   </soap:Body>
</soap:Envelope>